setup_client.py
client/__init__.py
client/client_db.py
client/client_gui.py
client/main_window.py
client/new_contact.py
client/remove_contact.py
client/start_dialog.py
client/transport.py
clientapp.egg-info/PKG-INFO
clientapp.egg-info/SOURCES.txt
clientapp.egg-info/dependency_links.txt
clientapp.egg-info/requires.txt
clientapp.egg-info/top_level.txt
common/__init__.py
common/decors.py
common/descriptrs.py
common/metaclasses.py
common/utils.py
common/variables.py
logs/__init__.py
logs/config/__init__.py
logs/config/config_log_client.py
logs/log-files/__init__.py