Metadata-Version: 2.1
Name: clientapp
Version: 0.1
Summary: serverapp
Home-page: UNKNOWN
Author: Korepanov A
Author-email: al1working@mail.ru
License: UNKNOWN
Platform: UNKNOWN
